aiodbm/__init__.py
aiodbm/core.py
aiodbm/threads.py
aiodbm-0.4.2.dist-info/LICENSE
aiodbm-0.4.2.dist-info/WHEEL
aiodbm-0.4.2.dist-info/METADATA
aiodbm-0.4.2.dist-info/RECORD
