Metadata-Version: 2.1
Name: aiodbm
Version: 0.4.2
Summary: An AsyncIO bridge for DBM.
Author-email: Erik Kalkoken <kalkoken87@gmail.com>
Requires-Python: >=3.8
Classifier: License :: OSI Approved :: MIT License
Classifier: Programming Language :: Python
Classifier: Programming Language :: Python :: 3.8
Classifier: Programming Language :: Python :: 3.9
Classifier: Programming Language :: Python :: 3.10
Classifier: Programming Language :: Python :: 3.11
Project-URL: Documentation, https://aiodbm.readthedocs.io/en/latest/
Project-URL: Source, https://github.com/ErikKalkoken/aiodbm
Project-URL: Tracker, https://github.com/ErikKalkoken/aiodbm/issues
